{
    "phonetic": {
        "\uff01": "!",
        "\uff1f": "?",
        "\u30a2": "a",
        "\u30a4": "i",
        "\u30a4\u30a7": "j e",
        "\u30a6": "M",
        "\u30a6\u30a3": "w i",
        "\u30a6\u30a7": "w e",
        "\u30a6\u30a9": "w o",
        "\u30a8": "e",
        "\u30aa": "o",
        "\u30f2": "o",
        "\u30ab": "k a",
        "\u30ac": "g a",
        "\u30ad": "k' i",
        "\u30ad\u30a7": "k' e",
        "\u30ad\u30e3": "k' a",
        "\u30ad\u30e5": "k' M",
        "\u30ad\u30e7": "k' o",
        "\u30ae": "g' i",
        "\u30ae\u30a7": "g' e",
        "\u30ae\u30e3": "g' a",
        "\u30ae\u30e5": "g' M",
        "\u30ae\u30e7": "g' o",
        "\u30af": "k M",
        "\u30b0": "g M",
        "\u30b1": "k e",
        "\u30b2": "g e",
        "\u30b3": "k o",
        "\u30b4": "g o",
        "\u30b5": "s a",
        "\u30b6": "dz a",
        "\u30b7": "S i",
        "\u30b7\u30a7": "S e",
        "\u30b7\u30e3": "S a",
        "\u30b7\u30e5": "S M",
        "\u30b7\u30e7": "S o",
        "\u30b8": "dZ i",
        "\u30c2": "dZ i",
        "\u30b8\u30a7": "dZ e",
        "\u30b8\u30e3": "dZ a",
        "\u30b8\u30e5": "dZ M",
        "\u30b8\u30e7": "dZ o",
        "\u30b9": "s M",
        "\u30b9\u30a3": "s i",
        "\u30ba": "dz M",
        "\u30c5": "dz M",
        "\u30ba\u30a3": "dz i",
        "\u30bb": "s e",
        "\u30bc": "dz e",
        "\u30bd": "s o",
        "\u30be": "dz o",
        "\u30bf": "t a",
        "\u30c0": "d a",
        "\u30c1": "tS i",
        "\u30c1\u30a7": "tS e",
        "\u30c1\u30e3": "tS a",
        "\u30c1\u30e5": "tS M",
        "\u30c1\u30e7": "tS o",
        "\u30c4": "ts M",
        "\u30c4\u30a1": "ts a",
        "\u30c4\u30a3": "ts i",
        "\u30c4\u30a7": "ts e",
        "\u30c4\u30a9": "ts o",
        "\u30c6": "t e",
        "\u30c6\u30a3": "t' i",
        "\u30c6\u30a7": "t' e",
        "\u30c6\u30e3": "t' a",
        "\u30c6\u30e5": "t' M",
        "\u30c6\u30e7": "t' o",
        "\u30c7": "d e",
        "\u30c7\u30a3": "d' i",
        "\u30c7\u30a7": "d' e",
        "\u30c7\u30e3": "d' a",
        "\u30c7\u30e5": "d' M",
        "\u30c7\u30e7": "d' o",
        "\u30c8": "t o",
        "\u30c8\u30a5": "t M",
        "\u30c9": "d o",
        "\u30c9\u30a5": "d M",
        "\u30ca": "n a",
        "\u30cb": "J i",
        "\u30cb\u30a7": "J e",
        "\u30cb\u30e3": "J a",
        "\u30cb\u30e5": "J M",
        "\u30cb\u30e7": "J o",
        "\u30cc": "n M",
        "\u30cd": "n e",
        "\u30ce": "n o",
        "\u30cf": "h a",
        "\u30d0": "b a",
        "\u30d1": "p a",
        "\u30d2": "C i",
        "\u30d2\u30a7": "C e",
        "\u30d2\u30e3": "C a",
        "\u30d2\u30e5": "C M",
        "\u30d2\u30e7": "C o",
        "\u30d3": "b' i",
        "\u30d3\u30a7": "b' e",
        "\u30d3\u30e3": "b' a",
        "\u30d3\u30e5": "b' M",
        "\u30d3\u30e7": "b' o",
        "\u30d4": "p' i",
        "\u30d4\u30a7": "p' e",
        "\u30d4\u30e3": "p' a",
        "\u30d4\u30e5": "p' M",
        "\u30d4\u30e7": "p' o",
        "\u30d5": "p\\ M",
        "\u30d5\u30a1": "p\\ a",
        "\u30d5\u30a3": "p\\' i",
        "\u30d5\u30a7": "p\\ e",
        "\u30d5\u30a9": "p\\ o",
        "\u30d5\u30e3": "p\\' a",
        "\u30d5\u30e5": "p\\' M",
        "\u30d6": "b M",
        "\u30f4": "b M",
        "\u30d7": "p M",
        "\u30d8": "h e",
        "\u30d9": "b e",
        "\u30da": "p e",
        "\u30db": "h o",
        "\u30dc": "b o",
        "\u30dd": "p o",
        "\u30de": "m a",
        "\u30df": "m' i",
        "\u30df\u30a7": "m' e",
        "\u30df\u30e3": "m' a",
        "\u30df\u30e5": "m' M",
        "\u30df\u30e7": "m' o",
        "\u30e0": "m M",
        "\u30e1": "m e",
        "\u30e2": "m o",
        "\u30e4": "j a",
        "\u30e6": "j M",
        "\u30e8": "j o",
        "\u30e9": "4 a",
        "\u30ea": "4' i",
        "\u30ea\u30a7": "4' e",
        "\u30ea\u30e3": "4' a",
        "\u30ea\u30e5": "4' M",
        "\u30ea\u30e7": "4' o",
        "\u30eb": "4 M",
        "\u30ec": "4 e",
        "\u30ed": "4 o",
        "\u30ef": "w a",
        "\u30f3": "n",
        "\u30fc": "-",
        "\u30ea\u30e3SS": "4'",
        "\u30e9SS": "4",
        "\u30d2SS": "C",
        "\u30b7SS": "S",
        "\u30d3SS": "b'",
        "\u30d0SS": "b",
        "\u30c7\u30a3SS": "d'",
        "\u30c0SS": "d",
        "\u30b8\u30e3SS": "dZ",
        "\u30b6SS": "dz",
        "\u30ae\u30e3SS": "g'",
        "\u30acSS": "g",
        "\u30cfSS": "h",
        "\u30e4SS": "j",
        "\u30ad\u30e3SS": "k'",
        "\u30abSS": "k",
        "\u30d4\u30e3SS": "p'",
        "\u30d1SS": "p",
        "\u30d5SS": "p\\",
        "\u30b5SS": "s",
        "\u30c6\u30a3SS": "t'",
        "\u30bfSS": "t",
        "\u30c1SS": "tS",
        "\u30c4SS": "ts",
        "\u30efSS": "w",
        "\u3042": "a",
        "\u3044": "i",
        "\u3044\u3047": "j e",
        "\u3046": "M",
        "\u3046\u3043": "w i",
        "\u3046\u3047": "w e",
        "\u3046\u3049": "w o",
        "\u3048": "e",
        "\u304a": "o",
        "\u3092": "o",
        "\u304b": "k a",
        "\u304c": "g a",
        "\u304d": "k' i",
        "\u304d\u3047": "k' e",
        "\u304d\u3083": "k' a",
        "\u304d\u3085": "k' M",
        "\u304d\u3087": "k' o",
        "\u304e": "g' i",
        "\u304e\u3047": "g' e",
        "\u304e\u3083": "g' a",
        "\u304e\u3085": "g' M",
        "\u304e\u3087": "g' o",
        "\u304f": "k M",
        "\u3050": "g M",
        "\u3051": "k e",
        "\u3052": "g e",
        "\u3053": "k o",
        "\u3054": "g o",
        "\u3055": "s a",
        "\u3056": "dz a",
        "\u3057": "S i",
        "\u3057\u3047": "S e",
        "\u3057\u3083": "S a",
        "\u3057\u3085": "S M",
        "\u3057\u3087": "S o",
        "\u3058": "dZ i",
        "\u3062": "dZ i",
        "\u3058\u3047": "dZ e",
        "\u3058\u3083": "dZ a",
        "\u3058\u3085": "dZ M",
        "\u3058\u3087": "dZ o",
        "\u3059": "s M",
        "\u3059\u3043": "s i",
        "\u305a": "dz M",
        "\u3065": "dz M",
        "\u305a\u3043": "dz i",
        "\u305b": "s e",
        "\u305c": "dz e",
        "\u305d": "s o",
        "\u305e": "dz o",
        "\u305f": "t a",
        "\u3060": "d a",
        "\u3061": "tS i",
        "\u3061\u3047": "tS e",
        "\u3061\u3083": "tS a",
        "\u3061\u3085": "tS M",
        "\u3061\u3087": "tS o",
        "\u3064": "ts M",
        "\u3064\u3041": "ts a",
        "\u3064\u3043": "ts i",
        "\u3064\u3047": "ts e",
        "\u3064\u3049": "ts o",
        "\u3066": "t e",
        "\u3066\u3043": "t' i",
        "\u3066\u3047": "t' e",
        "\u3066\u3083": "t' a",
        "\u3066\u3085": "t' M",
        "\u3066\u3087": "t' o",
        "\u3067": "d e",
        "\u3067\u3043": "d' i",
        "\u3067\u3047": "d' e",
        "\u3067\u3083": "d' a",
        "\u3067\u3085": "d' M",
        "\u3067\u3087": "d' o",
        "\u3068": "t o",
        "\u3068\u3045": "t M",
        "\u3069": "d o",
        "\u3069\u3045": "d M",
        "\u306a": "n a",
        "\u306b": "J i",
        "\u306b\u3047": "J e",
        "\u306b\u3083": "J a",
        "\u306b\u3085": "J M",
        "\u306b\u3087": "J o",
        "\u306c": "n M",
        "\u306d": "n e",
        "\u306e": "n o",
        "\u306f": "h a",
        "\u3070": "b a",
        "\u3071": "p a",
        "\u3072": "C i",
        "\u3072\u3047": "C e",
        "\u3072\u3083": "C a",
        "\u3072\u3085": "C M",
        "\u3072\u3087": "C o",
        "\u3073": "b' i",
        "\u3073\u3047": "b' e",
        "\u3073\u3083": "b' a",
        "\u3073\u3085": "b' M",
        "\u3073\u3087": "b' o",
        "\u3074": "p' i",
        "\u3074\u3047": "p' e",
        "\u3074\u3083": "p' a",
        "\u3074\u3085": "p' M",
        "\u3074\u3087": "p' o",
        "\u3075": "p\\ M",
        "\u3075\u3041": "p\\ a",
        "\u3075\u3043": "p\\' i",
        "\u3075\u3047": "p\\ e",
        "\u3075\u3049": "p\\ o",
        "\u3075\u3083": "p\\' a",
        "\u3075\u3085": "p\\' M",
        "\u3076": "b M",
        "\u3046\u309b": "b M",
        "\u3077": "p M",
        "\u3078": "h e",
        "\u3079": "b e",
        "\u307a": "p e",
        "\u307b": "h o",
        "\u307c": "b o",
        "\u307d": "p o",
        "\u307e": "m a",
        "\u307f": "m' i",
        "\u307f\u3047": "m' e",
        "\u307f\u3083": "m' a",
        "\u307f\u3085": "m' M",
        "\u307f\u3087": "m' o",
        "\u3080": "m M",
        "\u3081": "m e",
        "\u3082": "m o",
        "\u3084": "j a",
        "\u3086": "j M",
        "\u3088": "j o",
        "\u3089": "4 a",
        "\u308a": "4' i",
        "\u308a\u3047": "4' e",
        "\u308a\u3083": "4' a",
        "\u308a\u3085": "4' M",
        "\u308a\u3087": "4' o",
        "\u308b": "4 M",
        "\u308c": "4 e",
        "\u308d": "4 o",
        "\u308f": "w a",
        "\u3093": "n",
        "\u3063": "cl",
        "\u30c3": "cl",
        "a": "a",
        "i": "i",
        "u": "M",
        "e": "e",
        "o": "o",
        "n": "n",
        "ka": "k a",
        "ki": "k' i",
        "ku": "k M",
        "ke": "k e",
        "ko": "k o",
        "sa": "s a",
        "shi": "S i",
        "su": "s M",
        "se": "s e",
        "so": "s o",
        "ta": "t a",
        "chi": "tS i",
        "tsu": "ts M",
        "te": "t e",
        "to": "t o",
        "na": "n a",
        "ni": "J i",
        "nu": "n M",
        "ne": "n e",
        "no": "n o",
        "ha": "h a",
        "hi": "C i",
        "fu": "p\\ M",
        "he": "h e",
        "ho": "h o",
        "ma": "m a",
        "mi": "m' i",
        "mu": "m M",
        "me": "m e",
        "mo": "m o",
        "ya": "j a",
        "yu": "j M",
        "yo": "j o",
        "ra": "4 a",
        "ri": "4' i",
        "ru": "4 M",
        "re": "4 e",
        "ro": "4 o",
        "wa": "w a",
        "ga": "g a",
        "gi": "g' i",
        "gu": "g M",
        "ge": "g e",
        "go": "g o",
        "ji": "dZ i",
        "za": "dz a",
        "zu": "dz M",
        "ze": "dz e",
        "zo": "dz o",
        "da": "d a",
        "de": "d e",
        "do": "d o",
        "ba": "b a",
        "bi": "b' i",
        "bu": "b M",
        "be": "b e",
        "bo": "b o",
        "pa": "p a",
        "pi": "p' i",
        "pu": "p M",
        "pe": "p e",
        "po": "p o",
        "N": "n",
        "si": "S i",
        "sha": "S a",
        "sya": "S a",
        "shu": "S M",
        "syu": "S M",
        "she": "S e",
        "sye": "S e",
        "sho": "S o",
        "syo": "S o",
        "cha": "tS a",
        "tya": "tS a",
        "ti": "tS i",
        "chu": "tS M",
        "tyu": "tS M",
        "che": "tS e",
        "tye": "tS e",
        "cho": "tS o",
        "tyo": "tS o",
        "tu": "ts M",
        "hu": "p\\ M",
        "fa": "p\\ a",
        "fi": "p\\' i",
        "fe": "p\\ e",
        "fo": "p\\ o",
        "yi": "i",
        "ye": "j e",
        "la": "4 a",
        "li": "4' i",
        "lu": "4 M",
        "le": "4 e",
        "lo": "4 o",
        "wi": "w i",
        "wu": "M",
        "we": "w e",
        "wo": "w o",
        "ja": "dZ a",
        "ju": "dZ M",
        "je": "dZ e",
        "jo": "dZ o",
        "jya": "dZ a",
        "jyi": "dZ i",
        "jyu": "dZ M",
        "jye": "dZ e",
        "jyo": "dZ o",
        "zi": "dZ i",
        "di": "d' i",
        "du": "d M",
        "va": "b a",
        "vi": "b' i",
        "vu": "b M",
        "ve": "b e",
        "vo": "b o",
        "kya": "k' a",
        "kyi": "k' i",
        "kyu": "k' M",
        "kye": "k' e",
        "kyo": "k' o",
        "tyi": "tS i",
        "dya": "d a",
        "dyi": "d' i",
        "dyu": "d M",
        "dye": "d' e",
        "dyo": "d' o",
        "nya": "J a",
        "nyi": "J i",
        "nyu": "J M",
        "nye": "J e",
        "nyo": "J o",
        "hya": "C a",
        "hyi": "C i",
        "hyu": "C M",
        "hye": "C e",
        "hyo": "C o",
        "mya": "m' a",
        "myi": "m' i",
        "myu": "m' M",
        "mye": "m' e",
        "myo": "m' o",
        "rya": "4' a",
        "ryi": "4' i",
        "ryu": "4' M",
        "rye": "4' e",
        "ryo": "4' o",
        "gya": "g' a",
        "gyi": "g' i",
        "gyu": "g' M",
        "gye": "g' e",
        "gyo": "g' o",
        "bya": "b' a",
        "byi": "b' i",
        "byu": "b' M",
        "bye": "b' e",
        "byo": "b' o",
        "pya": "p' a",
        "pyi": "p' i",
        "pyu": "p' M",
        "pye": "p' e",
        "pyo": "p' o",
        "kka": "k a",
        "kki": "k' i",
        "kku": "k M",
        "kke": "k e",
        "kko": "k o",
        "ssa": "s a",
        "ssi": "S i",
        "ssu": "s M",
        "sse": "s e",
        "sso": "s o",
        "ssha": "S a",
        "sshi": "S i",
        "sshu": "S M",
        "sshe": "S e",
        "ssho": "S o",
        "ccha": "tS a",
        "cchi": "tS i",
        "cchu": "tS M",
        "cche": "tS e",
        "ccho": "tS o",
        "tsa": "ts a",
        "tsi": "ts i",
        "tse": "ts e",
        "tso": "ts o",
        "ttsa": "ts a",
        "ttsi": "ts i",
        "ttsu": "ts M",
        "ttse": "ts e",
        "ttso": "ts o",
        "tta": "t a",
        "tti": "tS i",
        "ttu": "ts M",
        "tte": "t e",
        "tto": "t o",
        "nna": "n a",
        "nni": "J i",
        "nnu": "n M",
        "nne": "n e",
        "nno": "n o",
        "hha": "h a",
        "hhi": "C i",
        "hhu": "p\\ M",
        "hhe": "h e",
        "hho": "h o",
        "ffa": "p\\ a",
        "ffi": "p\\' i",
        "ffu": "p\\ M",
        "ffe": "p\\ e",
        "ffo": "p\\ o",
        "mma": "m a",
        "mmi": "m' i",
        "mmu": "m M",
        "mme": "m e",
        "mmo": "m o",
        "yya": "j a",
        "yyi": "i",
        "yyu": "j M",
        "yye": "j e",
        "yyo": "j o",
        "rra": "4 a",
        "rri": "4' i",
        "rru": "4 M",
        "rre": "4 e",
        "rro": "4 o",
        "lla": "4 a",
        "lli": "4' i",
        "llu": "4 M",
        "lle": "4 e",
        "llo": "4 o",
        "wwa": "w a",
        "wwi": "w i",
        "wwu": "M",
        "wwe": "w e",
        "wwo": "w o",
        "gga": "g a",
        "ggi": "g' i",
        "ggu": "g M",
        "gge": "g e",
        "ggo": "g o",
        "jja": "dZ a",
        "jji": "dZ i",
        "jju": "dZ M",
        "jje": "dZ e",
        "jjo": "dZ o",
        "jjya": "dZ a",
        "jjyi": "dZ i",
        "jjyu": "dZ M",
        "jjye": "dZ e",
        "jjyo": "dZ o",
        "zza": "dz a",
        "zzi": "dZ i",
        "zzu": "dz M",
        "zze": "dz e",
        "zzo": "dz o",
        "dda": "d a",
        "ddi": "d' i",
        "ddu": "d M",
        "dde": "d e",
        "ddo": "d o",
        "bba": "b a",
        "bbi": "b' i",
        "bbu": "b M",
        "bbe": "b e",
        "bbo": "b o",
        "vva": "b a",
        "vvi": "b' i",
        "vvu": "b M",
        "vve": "b e",
        "vvo": "b o",
        "ppa": "p a",
        "ppi": "p' i",
        "ppu": "p M",
        "ppe": "p e",
        "ppo": "p o",
        "kkya": "k' a",
        "kkyi": "k' i",
        "kkyu": "k' M",
        "kkye": "k' e",
        "kkyo": "k' o",
        "ttya": "tS a",
        "ttyi": "tS i",
        "ttyu": "tS M",
        "ttye": "tS e",
        "ttyo": "tS o",
        "ddya": "d a",
        "ddyi": "d' i",
        "ddyu": "d M",
        "ddye": "d' e",
        "ddyo": "d' o",
        "nnya": "J a",
        "nnyi": "J i",
        "nnyu": "J M",
        "nnye": "J e",
        "nnyo": "J o",
        "hhya": "C a",
        "hhyi": "C i",
        "hhyu": "C M",
        "hhye": "C e",
        "hhyo": "C o",
        "mmya": "m' a",
        "mmyi": "m' i",
        "mmyu": "m' M",
        "mmye": "m' e",
        "mmyo": "m' o",
        "rrya": "4' a",
        "rryi": "4' i",
        "rryu": "4' M",
        "rrye": "4' e",
        "rryo": "4' o",
        "ggya": "g' a",
        "ggyi": "g' i",
        "ggyu": "g' M",
        "ggye": "g' e",
        "ggyo": "g' o",
        "bbya": "b' a",
        "bbyi": "b' i",
        "bbyu": "b' M",
        "bbye": "b' e",
        "bbyo": "b' o",
        "ppya": "p' a",
        "ppyi": "p' i",
        "ppyu": "p' M",
        "ppye": "p' e",
        "ppyo": "p' o"
    },
    "hira": {
        "a": "\u3042",
        "i": "\u3044",
        "j e": "\u3044\u3047",
        "M": "\u3046",
        "w i": "\u3046\u3043",
        "w e": "\u3046\u3047",
        "w o": "\u3046\u3049",
        "e": "\u3048",
        "o": "\u304a",
        "k a": "\u304b",
        "g a": "\u304c",
        "k' i": "\u304d",
        "k' e": "\u304d\u3047",
        "k' a": "\u304d\u3083",
        "k' M": "\u304d\u3085",
        "k' o": "\u304d\u3087",
        "g' i": "\u304e",
        "g' e": "\u304e\u3047",
        "g' a": "\u304e\u3083",
        "g' M": "\u304e\u3085",
        "g' o": "\u304e\u3087",
        "k M": "\u304f",
        "g M": "\u3050",
        "k e": "\u3051",
        "g e": "\u3052",
        "k o": "\u3053",
        "g o": "\u3054",
        "s a": "\u3055",
        "dz a": "\u3056",
        "S i": "\u3057",
        "S e": "\u3057\u3047",
        "S a": "\u3057\u3083",
        "S M": "\u3057\u3085",
        "S o": "\u3057\u3087",
        "dZ i": "\u3062",
        "dZ e": "\u3058\u3047",
        "dZ a": "\u3058\u3083",
        "dZ M": "\u3058\u3085",
        "dZ o": "\u3058\u3087",
        "s M": "\u3059",
        "s i": "\u3059\u3043",
        "dz M": "\u3065",
        "dz i": "\u305a\u3043",
        "s e": "\u305b",
        "dz e": "\u305c",
        "s o": "\u305d",
        "dz o": "\u305e",
        "t a": "\u305f",
        "d a": "\u3060",
        "tS i": "\u3061",
        "tS e": "\u3061\u3047",
        "tS a": "\u3061\u3083",
        "tS M": "\u3061\u3085",
        "tS o": "\u3061\u3087",
        "ts M": "\u3064",
        "ts a": "\u3064\u3041",
        "ts i": "\u3064\u3043",
        "ts e": "\u3064\u3047",
        "ts o": "\u3064\u3049",
        "t e": "\u3066",
        "t' i": "\u3066\u3043",
        "t' e": "\u3066\u3047",
        "t' a": "\u3066\u3083",
        "t' M": "\u3066\u3085",
        "t' o": "\u3066\u3087",
        "d e": "\u3067",
        "d' i": "\u3067\u3043",
        "d' e": "\u3067\u3047",
        "d' a": "\u3067\u3083",
        "d' M": "\u3067\u3085",
        "d' o": "\u3067\u3087",
        "t o": "\u3068",
        "t M": "\u3068\u3045",
        "d o": "\u3069",
        "d M": "\u3069\u3045",
        "n a": "\u306a",
        "J i": "\u306b",
        "J e": "\u306b\u3047",
        "J a": "\u306b\u3083",
        "J M": "\u306b\u3085",
        "J o": "\u306b\u3087",
        "n M": "\u306c",
        "n e": "\u306d",
        "n o": "\u306e",
        "h a": "\u306f",
        "b a": "\u3070",
        "p a": "\u3071",
        "C i": "\u3072",
        "C e": "\u3072\u3047",
        "C a": "\u3072\u3083",
        "C M": "\u3072\u3085",
        "C o": "\u3072\u3087",
        "b' i": "\u3073",
        "b' e": "\u3073\u3047",
        "b' a": "\u3073\u3083",
        "b' M": "\u3073\u3085",
        "b' o": "\u3073\u3087",
        "p' i": "\u3074",
        "p' e": "\u3074\u3047",
        "p' a": "\u3074\u3083",
        "p' M": "\u3074\u3085",
        "p' o": "\u3074\u3087",
        "p\\ M": "\u3075",
        "p\\ a": "\u3075\u3041",
        "p\\' i": "\u3075\u3043",
        "p\\ e": "\u3075\u3047",
        "p\\ o": "\u3075\u3049",
        "p\\' a": "\u3075\u3083",
        "p\\' M": "\u3075\u3085",
        "b M": "\u3046\u309b",
        "p M": "\u3077",
        "h e": "\u3078",
        "b e": "\u3079",
        "p e": "\u307a",
        "h o": "\u307b",
        "b o": "\u307c",
        "p o": "\u307d",
        "m a": "\u307e",
        "m' i": "\u307f",
        "m' e": "\u307f\u3047",
        "m' a": "\u307f\u3083",
        "m' M": "\u307f\u3085",
        "m' o": "\u307f\u3087",
        "m M": "\u3080",
        "m e": "\u3081",
        "m o": "\u3082",
        "j a": "\u3084",
        "j M": "\u3086",
        "j o": "\u3088",
        "4 a": "\u3089",
        "4' i": "\u308a",
        "4' e": "\u308a\u3047",
        "4' a": "\u308a\u3083",
        "4' M": "\u308a\u3085",
        "4' o": "\u308a\u3087",
        "4 M": "\u308b",
        "4 e": "\u308c",
        "4 o": "\u308d",
        "w a": "\u308f",
        "n": "\u3093",
        "cl": "\u3063"
    },
    "dic": {
        "\u3042": [
            "a",
            "a_0",
            "a",
            "a_0"
        ],
        "\u3044": [
            "i",
            "i_0",
            "i",
            "i_0"
        ],
        "\u3044\u3047": [
            "j e",
            "j_0 e_0",
            "j_0 e",
            "j e_0"
        ],
        "\u3046": [
            "M",
            "M_0",
            "M",
            "M_0"
        ],
        "\u3046\u3043": [
            "w i",
            "w_0 i_0",
            "w_0 i",
            "w i_0"
        ],
        "\u3046\u3047": [
            "w e",
            "w_0 e_0",
            "w_0 e",
            "w e_0"
        ],
        "\u3046\u3049": [
            "w o",
            "w_0 o_0",
            "w_0 o",
            "w o_0"
        ],
        "\u3048": [
            "e",
            "e_0",
            "e",
            "e_0"
        ],
        "\u304a": [
            "o",
            "o_0",
            "o",
            "o_0"
        ],
        "\u3092": [
            "o",
            "o_0",
            "o",
            "o_0"
        ],
        "\u304b": [
            "k a",
            "k_0 a_0",
            "k_0 a",
            "k a_0"
        ],
        "\u304c": [
            "g a",
            "g_0 a_0",
            "g_0 a",
            "g a_0"
        ],
        "\u304d": [
            "k' i",
            "k'_0 i_0",
            "k'_0 i",
            "k' i_0"
        ],
        "\u304d\u3047": [
            "k' e",
            "k'_0 e_0",
            "k'_0 e",
            "k' e_0"
        ],
        "\u304d\u3083": [
            "k' a",
            "k'_0 a_0",
            "k'_0 a",
            "k' a_0"
        ],
        "\u304d\u3085": [
            "k' M",
            "k'_0 M_0",
            "k'_0 M",
            "k' M_0"
        ],
        "\u304d\u3087": [
            "k' o",
            "k'_0 o_0",
            "k'_0 o",
            "k' o_0"
        ],
        "\u304e": [
            "g' i",
            "g'_0 i_0",
            "g'_0 i",
            "g' i_0"
        ],
        "\u304e\u3047": [
            "g' e",
            "g'_0 e_0",
            "g'_0 e",
            "g' e_0"
        ],
        "\u304e\u3083": [
            "g' a",
            "g'_0 a_0",
            "g'_0 a",
            "g' a_0"
        ],
        "\u304e\u3085": [
            "g' M",
            "g'_0 M_0",
            "g'_0 M",
            "g' M_0"
        ],
        "\u304e\u3087": [
            "g' o",
            "g'_0 o_0",
            "g'_0 o",
            "g' o_0"
        ],
        "\u304f": [
            "k M",
            "k_0 M_0",
            "k_0 M",
            "k M_0"
        ],
        "\u3050": [
            "g M",
            "g_0 M_0",
            "g_0 M",
            "g M_0"
        ],
        "\u3051": [
            "k e",
            "k_0 e_0",
            "k_0 e",
            "k e_0"
        ],
        "\u3052": [
            "g e",
            "g_0 e_0",
            "g_0 e",
            "g e_0"
        ],
        "\u3053": [
            "k o",
            "k_0 o_0",
            "k_0 o",
            "k o_0"
        ],
        "\u3054": [
            "g o",
            "g_0 o_0",
            "g_0 o",
            "g o_0"
        ],
        "\u3055": [
            "s a",
            "s_0 a_0",
            "s_0 a",
            "s a_0"
        ],
        "\u3056": [
            "dz a",
            "dz_0 a_0",
            "dz_0 a",
            "dz a_0"
        ],
        "\u3057": [
            "S i",
            "S_0 i_0",
            "S_0 i",
            "S i_0"
        ],
        "\u3057\u3047": [
            "S e",
            "S_0 e_0",
            "S_0 e",
            "S e_0"
        ],
        "\u3057\u3083": [
            "S a",
            "S_0 a_0",
            "S_0 a",
            "S a_0"
        ],
        "\u3057\u3085": [
            "S M",
            "S_0 M_0",
            "S_0 M",
            "S M_0"
        ],
        "\u3057\u3087": [
            "S o",
            "S_0 o_0",
            "S_0 o",
            "S o_0"
        ],
        "\u3058": [
            "dZ i",
            "dZ_0 i_0",
            "dZ_0 i",
            "dZ i_0"
        ],
        "\u3062": [
            "dZ i",
            "dZ_0 i_0",
            "dZ_0 i",
            "dZ i_0"
        ],
        "\u3058\u3047": [
            "dZ e",
            "dZ_0 e_0",
            "dZ_0 e",
            "dZ e_0"
        ],
        "\u3058\u3083": [
            "dZ a",
            "dZ_0 a_0",
            "dZ_0 a",
            "dZ a_0"
        ],
        "\u3058\u3085": [
            "dZ M",
            "dZ_0 M_0",
            "dZ_0 M",
            "dZ M_0"
        ],
        "\u3058\u3087": [
            "dZ o",
            "dZ_0 o_0",
            "dZ_0 o",
            "dZ o_0"
        ],
        "\u3059": [
            "s M",
            "s_0 M_0",
            "s_0 M",
            "s M_0"
        ],
        "\u3059\u3043": [
            "s i",
            "s_0 i_0",
            "s_0 i",
            "s i_0"
        ],
        "\u305a": [
            "dz M",
            "dz_0 M_0",
            "dz_0 M",
            "dz M_0"
        ],
        "\u3065": [
            "dz M",
            "dz_0 M_0",
            "dz_0 M",
            "dz M_0"
        ],
        "\u305a\u3043": [
            "dz i",
            "dz_0 i_0",
            "dz_0 i",
            "dz i_0"
        ],
        "\u305b": [
            "s e",
            "s_0 e_0",
            "s_0 e",
            "s e_0"
        ],
        "\u305c": [
            "dz e",
            "dz_0 e_0",
            "dz_0 e",
            "dz e_0"
        ],
        "\u305d": [
            "s o",
            "s_0 o_0",
            "s_0 o",
            "s o_0"
        ],
        "\u305e": [
            "dz o",
            "dz_0 o_0",
            "dz_0 o",
            "dz o_0"
        ],
        "\u305f": [
            "t a",
            "t_0 a_0",
            "t_0 a",
            "t a_0"
        ],
        "\u3060": [
            "d a",
            "d_0 a_0",
            "d_0 a",
            "d a_0"
        ],
        "\u3061": [
            "tS i",
            "tS_0 i_0",
            "tS_0 i",
            "tS i_0"
        ],
        "\u3061\u3047": [
            "tS e",
            "tS_0 e_0",
            "tS_0 e",
            "tS e_0"
        ],
        "\u3061\u3083": [
            "tS a",
            "tS_0 a_0",
            "tS_0 a",
            "tS a_0"
        ],
        "\u3061\u3085": [
            "tS M",
            "tS_0 M_0",
            "tS_0 M",
            "tS M_0"
        ],
        "\u3061\u3087": [
            "tS o",
            "tS_0 o_0",
            "tS_0 o",
            "tS o_0"
        ],
        "\u3064": [
            "ts M",
            "ts_0 M_0",
            "ts_0 M",
            "ts M_0"
        ],
        "\u3064\u3041": [
            "ts a",
            "ts_0 a_0",
            "ts_0 a",
            "ts a_0"
        ],
        "\u3064\u3043": [
            "ts i",
            "ts_0 i_0",
            "ts_0 i",
            "ts i_0"
        ],
        "\u3064\u3047": [
            "ts e",
            "ts_0 e_0",
            "ts_0 e",
            "ts e_0"
        ],
        "\u3064\u3049": [
            "ts o",
            "ts_0 o_0",
            "ts_0 o",
            "ts o_0"
        ],
        "\u3066": [
            "t e",
            "t_0 e_0",
            "t_0 e",
            "t e_0"
        ],
        "\u3066\u3043": [
            "t' i",
            "t'_0 i_0",
            "t'_0 i",
            "t' i_0"
        ],
        "\u3066\u3047": [
            "t' e",
            "t'_0 e_0",
            "t'_0 e",
            "t' e_0"
        ],
        "\u3066\u3083": [
            "t' a",
            "t'_0 a_0",
            "t'_0 a",
            "t' a_0"
        ],
        "\u3066\u3085": [
            "t' M",
            "t'_0 M_0",
            "t'_0 M",
            "t' M_0"
        ],
        "\u3066\u3087": [
            "t' o",
            "t'_0 o_0",
            "t'_0 o",
            "t' o_0"
        ],
        "\u3067": [
            "d e",
            "d_0 e_0",
            "d_0 e",
            "d e_0"
        ],
        "\u3067\u3043": [
            "d' i",
            "d'_0 i_0",
            "d'_0 i",
            "d' i_0"
        ],
        "\u3067\u3047": [
            "d' e",
            "d'_0 e_0",
            "d'_0 e",
            "d' e_0"
        ],
        "\u3067\u3083": [
            "d' a",
            "d'_0 a_0",
            "d'_0 a",
            "d' a_0"
        ],
        "\u3067\u3085": [
            "d' M",
            "d'_0 M_0",
            "d'_0 M",
            "d' M_0"
        ],
        "\u3067\u3087": [
            "d' o",
            "d'_0 o_0",
            "d'_0 o",
            "d' o_0"
        ],
        "\u3068": [
            "t o",
            "t_0 o_0",
            "t_0 o",
            "t o_0"
        ],
        "\u3068\u3045": [
            "t M",
            "t_0 M_0",
            "t_0 M",
            "t M_0"
        ],
        "\u3069": [
            "d o",
            "d_0 o_0",
            "d_0 o",
            "d o_0"
        ],
        "\u3069\u3045": [
            "d M",
            "d_0 M_0",
            "d_0 M",
            "d M_0"
        ],
        "\u306a": [
            "n a",
            "n_0 a_0",
            "n_0 a",
            "n a_0"
        ],
        "\u306b": [
            "J i",
            "J_0 i_0",
            "J_0 i",
            "J i_0"
        ],
        "\u306b\u3047": [
            "J e",
            "J_0 e_0",
            "J_0 e",
            "J e_0"
        ],
        "\u306b\u3083": [
            "J a",
            "J_0 a_0",
            "J_0 a",
            "J a_0"
        ],
        "\u306b\u3085": [
            "J M",
            "J_0 M_0",
            "J_0 M",
            "J M_0"
        ],
        "\u306b\u3087": [
            "J o",
            "J_0 o_0",
            "J_0 o",
            "J o_0"
        ],
        "\u306c": [
            "n M",
            "n_0 M_0",
            "n_0 M",
            "n M_0"
        ],
        "\u306d": [
            "n e",
            "n_0 e_0",
            "n_0 e",
            "n e_0"
        ],
        "\u306e": [
            "n o",
            "n_0 o_0",
            "n_0 o",
            "n o_0"
        ],
        "\u306f": [
            "h a",
            "h_0 a_0",
            "h_0 a",
            "h a_0"
        ],
        "\u3070": [
            "b a",
            "b_0 a_0",
            "b_0 a",
            "b a_0"
        ],
        "\u3071": [
            "p a",
            "p_0 a_0",
            "p_0 a",
            "p a_0"
        ],
        "\u3072": [
            "C i",
            "C_0 i_0",
            "C_0 i",
            "C i_0"
        ],
        "\u3072\u3047": [
            "C e",
            "C_0 e_0",
            "C_0 e",
            "C e_0"
        ],
        "\u3072\u3083": [
            "C a",
            "C_0 a_0",
            "C_0 a",
            "C a_0"
        ],
        "\u3072\u3085": [
            "C M",
            "C_0 M_0",
            "C_0 M",
            "C M_0"
        ],
        "\u3072\u3087": [
            "C o",
            "C_0 o_0",
            "C_0 o",
            "C o_0"
        ],
        "\u3073": [
            "b' i",
            "b'_0 i_0",
            "b'_0 i",
            "b' i_0"
        ],
        "\u3073\u3047": [
            "b' e",
            "b'_0 e_0",
            "b'_0 e",
            "b' e_0"
        ],
        "\u3073\u3083": [
            "b' a",
            "b'_0 a_0",
            "b'_0 a",
            "b' a_0"
        ],
        "\u3073\u3085": [
            "b' M",
            "b'_0 M_0",
            "b'_0 M",
            "b' M_0"
        ],
        "\u3073\u3087": [
            "b' o",
            "b'_0 o_0",
            "b'_0 o",
            "b' o_0"
        ],
        "\u3074": [
            "p' i",
            "p'_0 i_0",
            "p'_0 i",
            "p' i_0"
        ],
        "\u3074\u3047": [
            "p' e",
            "p'_0 e_0",
            "p'_0 e",
            "p' e_0"
        ],
        "\u3074\u3083": [
            "p' a",
            "p'_0 a_0",
            "p'_0 a",
            "p' a_0"
        ],
        "\u3074\u3085": [
            "p' M",
            "p'_0 M_0",
            "p'_0 M",
            "p' M_0"
        ],
        "\u3074\u3087": [
            "p' o",
            "p'_0 o_0",
            "p'_0 o",
            "p' o_0"
        ],
        "\u3075": [
            "p\\ M",
            "p\\_0 M_0",
            "p\\_0 M",
            "p\\ M_0"
        ],
        "\u3075\u3041": [
            "p\\ a",
            "p\\_0 a_0",
            "p\\_0 a",
            "p\\ a_0"
        ],
        "\u3075\u3043": [
            "p\\' i",
            "p\\'_0 i_0",
            "p\\'_0 i",
            "p\\' i_0"
        ],
        "\u3075\u3047": [
            "p\\ e",
            "p\\_0 e_0",
            "p\\_0 e",
            "p\\ e_0"
        ],
        "\u3075\u3049": [
            "p\\ o",
            "p\\_0 o_0",
            "p\\_0 o",
            "p\\ o_0"
        ],
        "\u3075\u3083": [
            "p\\' a",
            "p\\'_0 a_0",
            "p\\'_0 a",
            "p\\' a_0"
        ],
        "\u3075\u3085": [
            "p\\' M",
            "p\\'_0 M_0",
            "p\\'_0 M",
            "p\\' M_0"
        ],
        "\u3076": [
            "b M",
            "b_0 M_0",
            "b_0 M",
            "b M_0"
        ],
        "\u3046\u309b": [
            "b M",
            "b_0 M_0",
            "b_0 M",
            "b M_0"
        ],
        "\u3077": [
            "p M",
            "p_0 M_0",
            "p_0 M",
            "p M_0"
        ],
        "\u3078": [
            "h e",
            "h_0 e_0",
            "h_0 e",
            "h e_0"
        ],
        "\u3079": [
            "b e",
            "b_0 e_0",
            "b_0 e",
            "b e_0"
        ],
        "\u307a": [
            "p e",
            "p_0 e_0",
            "p_0 e",
            "p e_0"
        ],
        "\u307b": [
            "h o",
            "h_0 o_0",
            "h_0 o",
            "h o_0"
        ],
        "\u307c": [
            "b o",
            "b_0 o_0",
            "b_0 o",
            "b o_0"
        ],
        "\u307d": [
            "p o",
            "p_0 o_0",
            "p_0 o",
            "p o_0"
        ],
        "\u307e": [
            "m a",
            "m_0 a_0",
            "m_0 a",
            "m a_0"
        ],
        "\u307f": [
            "m' i",
            "m'_0 i_0",
            "m'_0 i",
            "m' i_0"
        ],
        "\u307f\u3047": [
            "m' e",
            "m'_0 e_0",
            "m'_0 e",
            "m' e_0"
        ],
        "\u307f\u3083": [
            "m' a",
            "m'_0 a_0",
            "m'_0 a",
            "m' a_0"
        ],
        "\u307f\u3085": [
            "m' M",
            "m'_0 M_0",
            "m'_0 M",
            "m' M_0"
        ],
        "\u307f\u3087": [
            "m' o",
            "m'_0 o_0",
            "m'_0 o",
            "m' o_0"
        ],
        "\u3080": [
            "m M",
            "m_0 M_0",
            "m_0 M",
            "m M_0"
        ],
        "\u3081": [
            "m e",
            "m_0 e_0",
            "m_0 e",
            "m e_0"
        ],
        "\u3082": [
            "m o",
            "m_0 o_0",
            "m_0 o",
            "m o_0"
        ],
        "\u3084": [
            "j a",
            "j_0 a_0",
            "j_0 a",
            "j a_0"
        ],
        "\u3086": [
            "j M",
            "j_0 M_0",
            "j_0 M",
            "j M_0"
        ],
        "\u3088": [
            "j o",
            "j_0 o_0",
            "j_0 o",
            "j o_0"
        ],
        "\u3089": [
            "4 a",
            "4_0 a_0",
            "4_0 a",
            "4 a_0"
        ],
        "\u308a": [
            "4' i",
            "4'_0 i_0",
            "4'_0 i",
            "4' i_0"
        ],
        "\u308a\u3047": [
            "4' e",
            "4'_0 e_0",
            "4'_0 e",
            "4' e_0"
        ],
        "\u308a\u3083": [
            "4' a",
            "4'_0 a_0",
            "4'_0 a",
            "4' a_0"
        ],
        "\u308a\u3085": [
            "4' M",
            "4'_0 M_0",
            "4'_0 M",
            "4' M_0"
        ],
        "\u308a\u3087": [
            "4' o",
            "4'_0 o_0",
            "4'_0 o",
            "4' o_0"
        ],
        "\u308b": [
            "4 M",
            "4_0 M_0",
            "4_0 M",
            "4 M_0"
        ],
        "\u308c": [
            "4 e",
            "4_0 e_0",
            "4_0 e",
            "4 e_0"
        ],
        "\u308d": [
            "4 o",
            "4_0 o_0",
            "4_0 o",
            "4 o_0"
        ],
        "\u308f": [
            "w a",
            "w_0 a_0",
            "w_0 a",
            "w a_0"
        ],
        "\u3093": [
            "n",
            "n_0",
            "n",
            "n_0"
        ],
        "\u3063": [
            "cl",
            "cl_0",
            "cl",
            "cl_0"
        ]
    }
}